pyphi/__about__.py
pyphi/__init__.py
pyphi/actual.py
pyphi/cache.py
pyphi/conf.py
pyphi/connectivity.py
pyphi/constants.py
pyphi/convert.py
pyphi/db.py
pyphi/direction.py
pyphi/distance.py
pyphi/distribution.py
pyphi/examples.py
pyphi/exceptions.py
pyphi/jsonify.py
pyphi/labels.py
pyphi/log.py
pyphi/macro.py
pyphi/memory.py
pyphi/network.py
pyphi/node.py
pyphi/partition.py
pyphi/registry.py
pyphi/subsystem.py
pyphi/timescale.py
pyphi/tpm.py
pyphi/utils.py
pyphi/validate.py
pyphi/compute/__init__.py
pyphi/compute/distance.py
pyphi/compute/network.py
pyphi/compute/parallel.py
pyphi/compute/subsystem.py
pyphi/data/hamming_matrices/0.npy
pyphi/data/hamming_matrices/1.npy
pyphi/data/hamming_matrices/2.npy
pyphi/data/hamming_matrices/3.npy
pyphi/data/hamming_matrices/4.npy
pyphi/data/hamming_matrices/5.npy
pyphi/data/hamming_matrices/6.npy
pyphi/data/hamming_matrices/7.npy
pyphi/data/hamming_matrices/8.npy
pyphi/data/hamming_matrices/9.npy
pyphi/data/partition_lists/0.npy
pyphi/data/partition_lists/1.npy
pyphi/data/partition_lists/2.npy
pyphi/data/partition_lists/3.npy
pyphi/data/partition_lists/4.npy
pyphi/data/partition_lists/5.npy
pyphi/data/partition_lists/6.npy
pyphi/data/partition_lists/7.npy
pyphi/data/partition_lists/8.npy
pyphi/data/partition_lists/9.npy
pyphi/models/__init__.py
pyphi/models/actual_causation.py
pyphi/models/cmp.py
pyphi/models/cuts.py
pyphi/models/fmt.py
pyphi/models/mechanism.py
pyphi/models/subsystem.py
pyphi-1.2.0.dist-info/LICENSE.md
pyphi-1.2.0.dist-info/METADATA
pyphi-1.2.0.dist-info/WHEEL
pyphi-1.2.0.dist-info/top_level.txt
pyphi-1.2.0.dist-info/RECORD
