Metadata-Version: 2.1
Name: pyphi
Version: 1.2.0
Summary: Python library for computing integrated information.
Home-page: http://github.com/wmayner/pyphi
Author: William GP Mayner
Author-email: wmayner@gmail.com
License: GNU General Public License v3.0
Project-URL: Bug Reports, https://github.com/wmayner/pyphi/issues
Project-URL: Documentation, https://pyphi.readthedocs.io
Project-URL: IIT Website, http://integratedinformationtheory.org/
Project-URL: Online Interface, http://integratedinformationtheory.org/calculate.html
Project-URL: User Group, https://groups.google.com/forum/#!forum/pyphi-users
Keywords: neuroscience causality causal-modeling causation integrated-information-theory iit integrated-information modeling
Platform: UNKNOWN
Classifier: Development Status :: 4 - Beta
Classifier: Intended Audience :: Developers
Classifier: Natural Language :: English
Classifier: License :: OSI Approved :: GNU General Public License v3 or later (GPLv3+)
Classifier: Programming Language :: Python :: 3.4
Classifier: Programming Language :: Python :: 3.5
Classifier: Programming Language :: Python :: 3.6
Classifier: Programming Language :: Python :: 3.7
Classifier: Topic :: Scientific/Engineering
